{
  "snapshot_source": "intelligence_snapshot_script",
  "snapshot_captured_at_utc": "2025-12-20T12:24:10.284568+00:00",
  "market_close": {
    "S&P 500": 6834.5,
    "DOW J": 48134.89,
    "NASDAQ": 23307.621,
    "VIX": 14.91
  },
  "polymarket_markets": [
    {
      "market_id": "will-trump-release-the-epstein-files-by-december-19-771",
      "question": "Will Trump release the Epstein files by December 19?",
      "category_label": "Geopolitics",
      "category_raw": null,
      "primary_outcome": "Yes",
      "probability": 99.85000000000001,
      "volume_24h": 21609267.654411025,
      "tags": [],
      "end_date": null,
      "created_at": "2025-12-02T13:21:35.709387Z",
      "days_to_deadline": null
    },
    {
      "market_id": "will-the-next-dutch-government-be-vvd-cda",
      "question": "Will the next Dutch government be VVD + CDA?",
      "category_label": "Geopolitics",
      "category_raw": null,
      "primary_outcome": "Yes",
      "probability": 0.05,
      "volume_24h": 3178291.33,
      "tags": [],
      "end_date": null,
      "created_at": "2025-10-13T23:55:49.774228Z",
      "days_to_deadline": null
    },
    {
      "market_id": "will-pedro-tinoco-de-faria-win-the-2026-portugal-presidential-election",
      "question": "Will Pedro Tinoco de Faria win the 2026 Portugal presidential election?",
      "category_label": "Geopolitics",
      "category_raw": null,
      "primary_outcome": "Yes",
      "probability": 0.05,
      "volume_24h": 2979033.1530000004,
      "tags": [],
      "end_date": "2026-01-25T14:00:00Z",
      "created_at": "2025-07-28T19:21:42.769982Z",
      "days_to_deadline": 36.06656008112269
    },
    {
      "market_id": "fed-decreases-interest-rates-by-50-bps-after-january-2026-meeting",
      "question": "Fed decreases interest rates by 50+ bps after January 2026 meeting?",
      "category_label": "Geopolitics",
      "category_raw": null,
      "primary_outcome": "Yes",
      "probability": 1.4500000000000002,
      "volume_24h": 1746139.6895350004,
      "tags": [],
      "end_date": "2026-01-28T00:00:00Z",
      "created_at": "2025-09-17T16:22:35.837625Z",
      "days_to_deadline": 38.48322674763889
    },
    {
      "market_id": "russia-x-ukraine-ceasefire-in-2025",
      "question": "Russia x Ukraine ceasefire in 2025?",
      "category_label": "Geopolitics",
      "category_raw": null,
      "primary_outcome": "Yes",
      "probability": 2.75,
      "volume_24h": 1432848.9738869998,
      "tags": [],
      "end_date": "2025-12-31T12:00:00Z",
      "created_at": "2024-12-29T18:47:35.140745Z",
      "days_to_deadline": 10.98322674755787
    },
    {
      "market_id": "will-tim-walz-win-the-2028-democratic-presidential-nomination-475",
      "question": "Will Tim Walz win the 2028 Democratic presidential nomination?",
      "category_label": "US Politics",
      "category_raw": null,
      "primary_outcome": "Yes",
      "probability": 0.75,
      "volume_24h": 1397955.0293420001,
      "tags": [],
      "end_date": "2028-11-07T00:00:00Z",
      "created_at": "2025-07-03T20:37:09.711295Z",
      "days_to_deadline": 1052.4832234717476
    },
    {
      "market_id": "will-trae-young-win-the-20252026-nba-mvp",
      "question": "Will Trae Young win the 2025–2026 NBA MVP?",
      "category_label": "US Politics",
      "category_raw": null,
      "primary_outcome": "Yes",
      "probability": 0.05,
      "volume_24h": 1227800,
      "tags": [],
      "end_date": "2026-06-10T00:00:00Z",
      "created_at": "2025-07-16T16:03:28.029504Z",
      "days_to_deadline": 171.48322347162036
    },
    {
      "market_id": "will-avatar-fire-and-ash-opening-weekend-box-office-be-greater-than-123m",
      "question": "Will \"Avatar: Fire and Ash\" Opening Weekend Box Office be greater than 123m?",
      "category_label": "US Politics",
      "category_raw": null,
      "primary_outcome": "Yes",
      "probability": 0.4,
      "volume_24h": 1195981.312559,
      "tags": [],
      "end_date": "2025-12-22T12:00:00Z",
      "created_at": "2025-12-01T19:36:56.758528Z",
      "days_to_deadline": 1.983223471527778
    },
    {
      "market_id": "will-antnio-filipe-win-the-2026-portugal-presidential-election",
      "question": "Will António Filipe win the 2026 Portugal presidential election?",
      "category_label": "US Politics",
      "category_raw": null,
      "primary_outcome": "Yes",
      "probability": 0.15,
      "volume_24h": 884805.28,
      "tags": [],
      "end_date": "2026-01-25T14:00:00Z",
      "created_at": "2025-07-28T19:21:46.164749Z",
      "days_to_deadline": 36.06655680480324
    },
    {
      "market_id": "will-bitcoin-reach-1000000-by-december-31-2025",
      "question": "Will Bitcoin reach $1,000,000 by December 31, 2025?",
      "category_label": "US Politics",
      "category_raw": null,
      "primary_outcome": "Yes",
      "probability": 0.35000000000000003,
      "volume_24h": 739131.6831620004,
      "tags": [],
      "end_date": "2025-12-31T12:00:00Z",
      "created_at": "2024-12-30T20:41:14.977618Z",
      "days_to_deadline": 10.983223471400462
    },
    {
      "market_id": "will-avatar-fire-and-ash-opening-weekend-box-office-be-between-112m-and-123m",
      "question": "Will \"Avatar: Fire and Ash\" Opening Weekend Box Office be between 112m and 123m?",
      "category_label": "Tech & AI",
      "category_raw": null,
      "primary_outcome": "Yes",
      "probability": 0.75,
      "volume_24h": 699332.5038150003,
      "tags": [],
      "end_date": "2025-12-22T12:00:00Z",
      "created_at": "2025-12-01T19:36:56.153984Z",
      "days_to_deadline": 1.983221026226852
    },
    {
      "market_id": "fed-increases-interest-rates-by-25-bps-after-january-2026-meeting",
      "question": "Fed increases interest rates by 25+ bps after January 2026 meeting?",
      "category_label": "Tech & AI",
      "category_raw": null,
      "primary_outcome": "Yes",
      "probability": 0.75,
      "volume_24h": 689092.058119,
      "tags": [],
      "end_date": "2026-01-28T00:00:00Z",
      "created_at": "2025-09-17T16:22:39.874792Z",
      "days_to_deadline": 38.48322102609954
    },
    {
      "market_id": "will-curaao-win-the-2026-fifa-world-cup",
      "question": "Will Curaçao win the 2026 FIFA World Cup?",
      "category_label": "Tech & AI",
      "category_raw": null,
      "primary_outcome": "Yes",
      "probability": 0.05,
      "volume_24h": 641816.5700000001,
      "tags": [],
      "end_date": "2026-07-20T00:00:00Z",
      "created_at": "2025-07-02T16:55:06.231278Z",
      "days_to_deadline": 211.48322102603012
    },
    {
      "market_id": "will-saudi-aramco-be-the-second-largest-company-in-the-world-by-market-cap-on-december-31",
      "question": "Will Saudi Aramco be the second-largest company in the world by market cap on December 31?",
      "category_label": "Tech & AI",
      "category_raw": null,
      "primary_outcome": "Yes",
      "probability": 0.05,
      "volume_24h": 641672.445,
      "tags": [],
      "end_date": "2025-12-31T00:00:00Z",
      "created_at": "2025-10-10T21:22:40.051723Z",
      "days_to_deadline": 10.483221025960647
    },
    {
      "market_id": "will-nvidia-be-the-largest-company-in-the-world-by-market-cap-on-december-31-2025",
      "question": "Will NVIDIA be the largest company in the world by market cap on December 31?",
      "category_label": "Tech & AI",
      "category_raw": null,
      "primary_outcome": "Yes",
      "probability": 95.5,
      "volume_24h": 537937.5153630014,
      "tags": [],
      "end_date": "2025-12-31T12:00:00Z",
      "created_at": "2024-12-30T16:40:34.475787Z",
      "days_to_deadline": 10.983221025891204
    },
    {
      "market_id": "xi-jinping-out-in-2025",
      "question": "Xi Jinping out in 2025?",
      "category_label": "Science",
      "category_raw": null,
      "primary_outcome": "Yes",
      "probability": 0.65,
      "volume_24h": 487955.279821,
      "tags": [],
      "end_date": "2025-12-31T23:55:00Z",
      "created_at": "2025-06-12T17:36:33.023005Z",
      "days_to_deadline": 11.479746305347222
    },
    {
      "market_id": "will-avatar-fire-and-ash-opening-weekend-box-office-be-between-101m-and-112m",
      "question": "Will \"Avatar: Fire and Ash\" Opening Weekend Box Office be between 101m and 112m?",
      "category_label": "Science",
      "category_raw": null,
      "primary_outcome": "Yes",
      "probability": 1.7999999999999998,
      "volume_24h": 481434.0637369998,
      "tags": [],
      "end_date": "2025-12-22T12:00:00Z",
      "created_at": "2025-12-01T19:36:55.552573Z",
      "days_to_deadline": 1.9832185274421297
    },
    {
      "market_id": "over-10m-committed-to-the-gensyn-public-sale",
      "question": "Over $10M committed to the Gensyn public sale?",
      "category_label": "Science",
      "category_raw": null,
      "primary_outcome": "Yes",
      "probability": 99.85000000000001,
      "volume_24h": 480229.2509609998,
      "tags": [],
      "end_date": "2026-01-01T05:00:00Z",
      "created_at": "2025-12-15T20:42:58.600116Z",
      "days_to_deadline": 11.691551860706019
    },
    {
      "market_id": "will-athletic-club-win-the-202526-champions-league",
      "question": "Will Athletic Club win the 2025–26 Champions League?",
      "category_label": "Science",
      "category_raw": null,
      "primary_outcome": "Yes",
      "probability": 0.15,
      "volume_24h": 444033.83999999997,
      "tags": [],
      "end_date": "2026-05-31T00:00:00Z",
      "created_at": "2025-07-21T20:58:48.681423Z",
      "days_to_deadline": 161.48321852730325
    },
    {
      "market_id": "maduro-out-in-2025-411",
      "question": "Maduro out in 2025?",
      "category_label": "Science",
      "category_raw": null,
      "primary_outcome": "Yes",
      "probability": 3.85,
      "volume_24h": 432745.44934899994,
      "tags": [],
      "end_date": "2025-12-31T12:00:00Z",
      "created_at": "2024-12-31T18:11:41.090452Z",
      "days_to_deadline": 10.983218527222222
    }
  ],
  "top_headlines": [
    "6 Takeaways From the First Batch of the Epstein Files - The New York Times",
    "U.S. launches strikes in Syria targeting Islamic State fighters after American deaths - NPR",
    "Brown University and MIT shooting suspect found dead; identified as former grad student - ABC News",
    "Fact Sheet: President Donald J. Trump is Increasing Medical Marijuana and Cannabidiol Research - The White House (.gov)",
    "Trump's push to end transgender care for young people opposed by pediatricians - NPR",
    "City of Boulder To Close All Open Space and Mountain Parks Property Friday, Dec. 19 - City of Boulder (.gov)",
    "Elise Stefanik Tried Everything to Please Trump. He Still Jilted Her. - The New York Times",
    "PHOTOS: Kennedy Center adds Trump’s name to memorial Congress created for JFK - PBS"
  ],
  "trending_topics": [
    "Top trending searches of 2025 revealed by Google. See what made the list."
  ]
}