{
  "snapshot_source": "intelligence_snapshot_script",
  "snapshot_captured_at_utc": "2026-07-06T15:13:44.668399+00:00",
  "market_close": {
    "S&P 500": 7526.79,
    "DOW J": 52886.61,
    "NASDAQ": 26111.584,
    "VIX": 15.98
  },
  "polymarket_markets": [
    {
      "market_id": "will-norway-win-the-2026-fifa-world-cup-893",
      "question": "Will Norway win the 2026 FIFA World Cup?",
      "category_label": "Geopolitics",
      "category_raw": null,
      "primary_outcome": "Yes",
      "probability": 4.65,
      "volume_24h": 11998955.97474323,
      "tags": [],
      "end_date": "2026-07-20T00:00:00Z",
      "created_at": "2025-07-02T16:54:50.383881Z",
      "days_to_deadline": 13.365466754386574
    },
    {
      "market_id": "will-morocco-win-the-2026-fifa-world-cup-464",
      "question": "Will Morocco win the 2026 FIFA World Cup?",
      "category_label": "Geopolitics",
      "category_raw": null,
      "primary_outcome": "Yes",
      "probability": 2.55,
      "volume_24h": 6177326.672969012,
      "tags": [],
      "end_date": "2026-07-20T00:00:00Z",
      "created_at": "2025-07-02T16:54:57.522078Z",
      "days_to_deadline": 13.365466754085649
    },
    {
      "market_id": "will-usa-win-the-2026-fifa-world-cup-467",
      "question": "Will USA win the 2026 FIFA World Cup?",
      "category_label": "Geopolitics",
      "category_raw": null,
      "primary_outcome": "Yes",
      "probability": 3.25,
      "volume_24h": 5501747.409516989,
      "tags": [],
      "end_date": "2026-07-20T00:00:00Z",
      "created_at": "2025-07-02T16:54:46.301056Z",
      "days_to_deadline": 13.365466753993056
    },
    {
      "market_id": "will-england-win-the-2026-fifa-world-cup-937",
      "question": "Will England win the 2026 FIFA World Cup?",
      "category_label": "Geopolitics",
      "category_raw": null,
      "primary_outcome": "Yes",
      "probability": 14.45,
      "volume_24h": 4984368.170889026,
      "tags": [],
      "end_date": "2026-07-20T00:00:00Z",
      "created_at": "2025-07-02T16:54:41.473096Z",
      "days_to_deadline": 13.365466753923611
    },
    {
      "market_id": "will-egypt-win-the-2026-fifa-world-cup",
      "question": "Will Egypt win the 2026 FIFA World Cup?",
      "category_label": "Geopolitics",
      "category_raw": null,
      "primary_outcome": "Yes",
      "probability": 0.25,
      "volume_24h": 4281110.207097001,
      "tags": [],
      "end_date": "2026-07-20T00:00:00Z",
      "created_at": "2025-07-02T16:55:00.39017Z",
      "days_to_deadline": 13.365466753854166
    },
    {
      "market_id": "will-portugal-win-the-2026-fifa-world-cup-912",
      "question": "Will Portugal win the 2026 FIFA World Cup?",
      "category_label": "US Politics",
      "category_raw": null,
      "primary_outcome": "Yes",
      "probability": 5.8500000000000005,
      "volume_24h": 3940981.6297480064,
      "tags": [],
      "end_date": "2026-07-20T00:00:00Z",
      "created_at": "2025-07-02T16:54:44.492744Z",
      "days_to_deadline": 13.365464336412037
    },
    {
      "market_id": "fifwc-prt-esp-2026-07-06-team-to-advance",
      "question": "Portugal vs. Spain: Team to Advance",
      "category_label": "US Politics",
      "category_raw": null,
      "primary_outcome": "Yes",
      "probability": 33.5,
      "volume_24h": 3348480.6518100034,
      "tags": [],
      "end_date": "2026-07-06T19:00:00Z",
      "created_at": "2026-07-03T10:30:17.342423Z",
      "days_to_deadline": 0.1571310029398148
    },
    {
      "market_id": "will-belgium-win-the-2026-fifa-world-cup-358",
      "question": "Will Belgium win the 2026 FIFA World Cup?",
      "category_label": "US Politics",
      "category_raw": null,
      "primary_outcome": "Yes",
      "probability": 1.35,
      "volume_24h": 3345157.1930990103,
      "tags": [],
      "end_date": "2026-07-20T00:00:00Z",
      "created_at": "2025-07-02T16:54:47.961968Z",
      "days_to_deadline": 13.36546433619213
    },
    {
      "market_id": "will-switzerland-win-the-2026-fifa-world-cup",
      "question": "Will Switzerland win the 2026 FIFA World Cup?",
      "category_label": "US Politics",
      "category_raw": null,
      "primary_outcome": "Yes",
      "probability": 0.95,
      "volume_24h": 3081352.7076279996,
      "tags": [],
      "end_date": "2026-07-20T00:00:00Z",
      "created_at": "2025-07-02T16:55:03.947467Z",
      "days_to_deadline": 13.365464336111112
    },
    {
      "market_id": "fifwc-usa-bel-2026-07-06-team-to-advance",
      "question": "United States vs. Belgium: Team to Advance",
      "category_label": "US Politics",
      "category_raw": null,
      "primary_outcome": "Yes",
      "probability": 53.5,
      "volume_24h": 2819123.081288996,
      "tags": [],
      "end_date": "2026-07-07T00:00:00Z",
      "created_at": "2026-07-02T10:30:17.015942Z",
      "days_to_deadline": 0.36546433605324075
    },
    {
      "market_id": "will-gedion-timothewos-be-the-next-prime-minister-of-ethiopia",
      "question": "Will Gedion Timothewos be the next Prime Minister of Ethiopia?",
      "category_label": "Tech & AI",
      "category_raw": null,
      "primary_outcome": "Yes",
      "probability": 0.2,
      "volume_24h": 2818430.29,
      "tags": [],
      "end_date": "2026-06-01T00:00:00Z",
      "created_at": "2026-04-23T22:32:51.58945Z",
      "days_to_deadline": -35.6345392383912
    },
    {
      "market_id": "fifwc-prt-esp-2026-07-06-esp",
      "question": "Will Spain win on 2026-07-06?",
      "category_label": "Tech & AI",
      "category_raw": null,
      "primary_outcome": "Yes",
      "probability": 51.5,
      "volume_24h": 2564118.2310600197,
      "tags": [],
      "end_date": "2026-07-06T19:00:00Z",
      "created_at": "2026-07-03T10:00:04.563985Z",
      "days_to_deadline": 0.15712742813657407
    },
    {
      "market_id": "atp-minaur-cobolli-2026-07-06",
      "question": "Wimbledon ATP: Alex de Minaur vs Flavio Cobolli",
      "category_label": "Tech & AI",
      "category_raw": null,
      "primary_outcome": "Yes",
      "probability": 0.05,
      "volume_24h": 2497000.1068399977,
      "tags": [],
      "end_date": "2026-07-13T10:00:00Z",
      "created_at": "2026-07-04T22:00:06.686526Z",
      "days_to_deadline": 6.782127428055556
    },
    {
      "market_id": "will-spain-win-the-2026-fifa-world-cup-963",
      "question": "Will Spain win the 2026 FIFA World Cup?",
      "category_label": "Tech & AI",
      "category_raw": null,
      "primary_outcome": "Yes",
      "probability": 12.45,
      "volume_24h": 2420479.872237,
      "tags": [],
      "end_date": "2026-07-20T00:00:00Z",
      "created_at": "2025-07-02T16:54:40.860413Z",
      "days_to_deadline": 13.36546076130787
    },
    {
      "market_id": "wta-paolini-eala-2026-07-05",
      "question": "Wimbledon WTA: Jasmine Paolini vs Alexandra Eala",
      "category_label": "Tech & AI",
      "category_raw": null,
      "primary_outcome": "Yes",
      "probability": 99.95,
      "volume_24h": 2247060.873788001,
      "tags": [],
      "end_date": "2026-07-12T10:00:00Z",
      "created_at": "2026-07-04T16:00:08.064832Z",
      "days_to_deadline": 5.782127427905093
    },
    {
      "market_id": "will-colombia-win-the-2026-fifa-world-cup-734",
      "question": "Will Colombia win the 2026 FIFA World Cup?",
      "category_label": "Science",
      "category_raw": null,
      "primary_outcome": "Yes",
      "probability": 3.05,
      "volume_24h": 2176150.324478001,
      "tags": [],
      "end_date": "2026-07-20T00:00:00Z",
      "created_at": "2025-07-02T16:54:48.514643Z",
      "days_to_deadline": 13.36545879537037
    },
    {
      "market_id": "will-argentina-win-the-2026-fifa-world-cup-245",
      "question": "Will Argentina win the 2026 FIFA World Cup?",
      "category_label": "Science",
      "category_raw": null,
      "primary_outcome": "Yes",
      "probability": 16.650000000000002,
      "volume_24h": 2025895.2152520013,
      "tags": [],
      "end_date": "2026-07-20T00:00:00Z",
      "created_at": "2025-07-02T16:54:43.302408Z",
      "days_to_deadline": 13.365458795208335
    },
    {
      "market_id": "fifwc-usa-bel-2026-07-06-usa",
      "question": "Will United States win on 2026-07-06?",
      "category_label": "Science",
      "category_raw": null,
      "primary_outcome": "Yes",
      "probability": 38.5,
      "volume_24h": 2006410.3887979975,
      "tags": [],
      "end_date": "2026-07-07T00:00:00Z",
      "created_at": "2026-07-02T10:00:06.786718Z",
      "days_to_deadline": 0.36545879511574075
    },
    {
      "market_id": "will-france-win-the-2026-fifa-world-cup-924",
      "question": "Will France win the 2026 FIFA World Cup?",
      "category_label": "Science",
      "category_raw": null,
      "primary_outcome": "Yes",
      "probability": 32.75,
      "volume_24h": 1770299.6296900038,
      "tags": [],
      "end_date": "2026-07-20T00:00:00Z",
      "created_at": "2025-07-02T16:54:42.081862Z",
      "days_to_deadline": 13.365458795023148
    },
    {
      "market_id": "fifwc-prt-esp-2026-07-06-exact-score-3-3",
      "question": "Exact Score: Portugal 3 - 3 Spain?",
      "category_label": "Science",
      "category_raw": null,
      "primary_outcome": "Yes",
      "probability": 1.7500000000000002,
      "volume_24h": 1296092.9111010025,
      "tags": [],
      "end_date": "2026-07-06T19:00:00Z",
      "created_at": "2026-07-03T10:00:13.275564Z",
      "days_to_deadline": 0.15712546158564814
    }
  ],
  "top_headlines": [
    "Mourners throng funeral procession in Tehran for Iran's Supreme Leader Ayatollah Ali Khamenei - AP News",
    "Erdogan-Trump Friendship Can Help NATO, Turkey’s Foreign Minister Says - The New York Times",
    "Facing Threats, NATO Finds New Value in Turkey - The New York Times",
    "Zelenskyy demands Western support after Russian strikes kill 12 in Kyiv - politico.eu",
    "Accused Charlie Kirk assassin Tyler Robinson fights back as prosecutors' sprawling case comes into focus - Fox News",
    "How Trump Put Himself in the Middle of America’s 250th - The New York Times",
    "How President Trump got FIFA to rescind Folarin Balogin’s red card, while Belgium seethes - OregonLive.com",
    "Michigan Democratic Senate primary narrows to one-on-one matchup - The Hill"
  ],
  "trending_topics": [
    "YouTube Is Shutting Down Its General ‘Trending’ Video Page",
    "YouTube Will Get Rid of Its Main Trending List As Viewing Habits Shift",
    "YouTube is killing its Trending page a decade after its debut",
    "YouTube's 'Trending' Page is Shutting Down After a Decade",
    "YouTube’s ‘Trending’ section is about to disappear",
    "Google reveals the top trending searches of 2025",
    "YouTube removing the Trending page in favor of Charts, recommendations",
    "Gemini was Google’s top trending search term in 2025",
    "End of YouTube Trending: New Charts for Music, Podcasts, Trailers are Here",
    "Google’s Year in Search 2025: These trending topics spiked big"
  ]
}