{
  "snapshot_source": "intelligence_snapshot_script",
  "snapshot_captured_at_utc": "2026-03-13T12:38:44.519542+00:00",
  "market_close": {
    "S&P 500": 6672.62,
    "DOW J": 46677.85,
    "NASDAQ": 22311.98,
    "VIX": 25.97
  },
  "polymarket_markets": [
    {
      "market_id": "will-iran-close-the-strait-of-hormuz-by-march-31",
      "question": "Will Iran close the Strait of Hormuz by March 31?",
      "category_label": "Geopolitics",
      "category_raw": null,
      "primary_outcome": "Yes",
      "probability": 99.95,
      "volume_24h": 12463473.447043002,
      "tags": [],
      "end_date": "2026-12-31T00:00:00Z",
      "created_at": "2026-01-20T13:33:13.939196Z",
      "days_to_deadline": 292.4731114669097
    },
    {
      "market_id": "will-the-fed-decrease-interest-rates-by-50-bps-after-the-march-2026-meeting",
      "question": "Will the Fed decrease interest rates by 50+ bps after the March 2026 meeting?",
      "category_label": "Geopolitics",
      "category_raw": null,
      "primary_outcome": "Yes",
      "probability": 0.15,
      "volume_24h": 10110273.386000002,
      "tags": [],
      "end_date": "2026-03-18T00:00:00Z",
      "created_at": "2025-10-28T20:58:04.772334Z",
      "days_to_deadline": 4.47311146662037
    },
    {
      "market_id": "will-the-fed-increase-interest-rates-by-25-bps-after-the-march-2026-meeting",
      "question": "Will the Fed increase interest rates by 25+ bps after the March 2026 meeting?",
      "category_label": "Geopolitics",
      "category_raw": null,
      "primary_outcome": "Yes",
      "probability": 0.15,
      "volume_24h": 6848122.106999993,
      "tags": [],
      "end_date": "2026-03-18T00:00:00Z",
      "created_at": "2025-10-28T20:58:06.700202Z",
      "days_to_deadline": 4.473111466527778
    },
    {
      "market_id": "will-there-be-no-change-in-fed-interest-rates-after-the-march-2026-meeting",
      "question": "Will there be no change in Fed interest rates after the March 2026 meeting?",
      "category_label": "Geopolitics",
      "category_raw": null,
      "primary_outcome": "Yes",
      "probability": 99.45,
      "volume_24h": 5210414.427515993,
      "tags": [],
      "end_date": "2026-03-18T00:00:00Z",
      "created_at": "2025-10-28T20:58:06.095309Z",
      "days_to_deadline": 4.473111466458334
    },
    {
      "market_id": "will-the-fed-decrease-interest-rates-by-25-bps-after-the-march-2026-meeting",
      "question": "Will the Fed decrease interest rates by 25 bps after the March 2026 meeting?",
      "category_label": "Geopolitics",
      "category_raw": null,
      "primary_outcome": "Yes",
      "probability": 0.35000000000000003,
      "volume_24h": 4426548.58423201,
      "tags": [],
      "end_date": "2026-03-18T00:00:00Z",
      "created_at": "2025-10-28T20:58:05.284418Z",
      "days_to_deadline": 4.473111466388889
    },
    {
      "market_id": "will-iran-strike-israel-on-march-10",
      "question": "Will Iran strike Israel on March 10?",
      "category_label": "US Politics",
      "category_raw": null,
      "primary_outcome": "Yes",
      "probability": 97.45,
      "volume_24h": 2039094.088188999,
      "tags": [],
      "end_date": null,
      "created_at": "2026-02-28T16:24:26.287821Z",
      "days_to_deadline": null
    },
    {
      "market_id": "bitcoin-above-58k-on-march-13",
      "question": "Will the price of Bitcoin be above $58,000 on March 13?",
      "category_label": "US Politics",
      "category_raw": null,
      "primary_outcome": "Yes",
      "probability": 99.95,
      "volume_24h": 1803004.170114003,
      "tags": [],
      "end_date": "2026-03-13T16:00:00Z",
      "created_at": "2026-03-06T17:00:06.921018Z",
      "days_to_deadline": 0.1397743687384259
    },
    {
      "market_id": "will-the-iranian-regime-fall-by-april-30",
      "question": "Will the Iranian regime fall by April 30?",
      "category_label": "US Politics",
      "category_raw": null,
      "primary_outcome": "Yes",
      "probability": 14.499999999999998,
      "volume_24h": 1258901.1445740003,
      "tags": [],
      "end_date": "2026-04-30T00:00:00Z",
      "created_at": "2026-03-05T15:49:14.285097Z",
      "days_to_deadline": 47.47310770199074
    },
    {
      "market_id": "will-sarah-huckabee-sanders-win-the-2028-republican-presidential-nomination",
      "question": "Will Sarah Huckabee Sanders win the 2028 Republican presidential nomination?",
      "category_label": "US Politics",
      "category_raw": null,
      "primary_outcome": "Yes",
      "probability": 0.65,
      "volume_24h": 1178050.6800490003,
      "tags": [],
      "end_date": "2028-11-07T00:00:00Z",
      "created_at": "2025-07-10T16:58:07.96846Z",
      "days_to_deadline": 969.4731077019213
    },
    {
      "market_id": "elon-musk-of-tweets-march-13-march-20-20-39",
      "question": "Will Elon Musk post 20-39 tweets from March 13 to March 20, 2026?",
      "category_label": "US Politics",
      "category_raw": null,
      "primary_outcome": "Yes",
      "probability": 0.15,
      "volume_24h": 1077465.216,
      "tags": [],
      "end_date": "2026-03-20T16:00:00Z",
      "created_at": "2026-03-09T20:46:21.342179Z",
      "days_to_deadline": 7.139774368518518
    },
    {
      "market_id": "will-the-iranian-regime-fall-by-march-31",
      "question": "Will the Iranian regime fall by March 31?",
      "category_label": "Tech & AI",
      "category_raw": null,
      "primary_outcome": "Yes",
      "probability": 4.65,
      "volume_24h": 1059625.141143001,
      "tags": [],
      "end_date": "2026-03-31T00:00:00Z",
      "created_at": "2025-12-17T22:42:41.084713Z",
      "days_to_deadline": 17.47310367951389
    },
    {
      "market_id": "us-x-iran-ceasefire-by-march-31",
      "question": "US x Iran ceasefire by March 31?",
      "category_label": "Tech & AI",
      "category_raw": null,
      "primary_outcome": "Yes",
      "probability": 21.5,
      "volume_24h": 1057888.2778930007,
      "tags": [],
      "end_date": null,
      "created_at": "2026-02-28T13:44:02.41834Z",
      "days_to_deadline": null
    },
    {
      "market_id": "will-kristi-noem-win-the-2028-republican-presidential-nomination",
      "question": "Will Kristi Noem win the 2028 Republican presidential nomination?",
      "category_label": "Tech & AI",
      "category_raw": null,
      "primary_outcome": "Yes",
      "probability": 0.7000000000000001,
      "volume_24h": 990359.588108,
      "tags": [],
      "end_date": "2028-11-07T00:00:00Z",
      "created_at": "2025-07-10T16:58:14.999535Z",
      "days_to_deadline": 969.4731036793056
    },
    {
      "market_id": "will-iran-close-the-strait-of-hormuz-by-2027-969-911-654-431-667",
      "question": "Will Iran close the Strait of Hormuz before 2027?",
      "category_label": "Tech & AI",
      "category_raw": null,
      "primary_outcome": "Yes",
      "probability": 99.95,
      "volume_24h": 958052.0237799995,
      "tags": [],
      "end_date": "2026-12-31T00:00:00Z",
      "created_at": "2025-11-04T18:59:17.081407Z",
      "days_to_deadline": 292.47310367922455
    },
    {
      "market_id": "will-iran-close-the-strait-of-hormuz-by-june-30",
      "question": "Will Iran close the Strait of Hormuz by June 30?",
      "category_label": "Tech & AI",
      "category_raw": null,
      "primary_outcome": "Yes",
      "probability": 99.95,
      "volume_24h": 955198.0120209999,
      "tags": [],
      "end_date": "2026-06-30T00:00:00Z",
      "created_at": "2026-01-20T13:33:59.553909Z",
      "days_to_deadline": 108.4731036791551
    },
    {
      "market_id": "elon-musk-of-tweets-march-6-march-13-340-359",
      "question": "Will Elon Musk post 340-359 tweets from March 6 to March 13, 2026?",
      "category_label": "Science",
      "category_raw": null,
      "primary_outcome": "Yes",
      "probability": 5.35,
      "volume_24h": 877679.8929370004,
      "tags": [],
      "end_date": "2026-03-13T16:00:00Z",
      "created_at": "2026-03-03T05:00:08.603247Z",
      "days_to_deadline": 0.1397664328587963
    },
    {
      "market_id": "will-the-greens-win-the-second-most-seats-in-the-2026-baden-wrttemberg-parliamentary-elections",
      "question": "Will The Greens win the second most seats in the 2026 Baden-Württemberg parliamentary elections?",
      "category_label": "Science",
      "category_raw": null,
      "primary_outcome": "Yes",
      "probability": 0.05,
      "volume_24h": 820559.3579999999,
      "tags": [],
      "end_date": "2026-03-08T00:00:00Z",
      "created_at": "2026-02-10T21:19:51.277033Z",
      "days_to_deadline": -5.526900233946759
    },
    {
      "market_id": "russia-strike-impacts-kyiv-municipality-during-week-of-march-2-2026",
      "question": "Russia strike impacts Kyiv municipality during week of March 2, 2026?",
      "category_label": "Science",
      "category_raw": null,
      "primary_outcome": "Yes",
      "probability": 99.85000000000001,
      "volume_24h": 812509.3045240002,
      "tags": [],
      "end_date": null,
      "created_at": "2026-02-25T19:14:47.005912Z",
      "days_to_deadline": null
    },
    {
      "market_id": "sea-tor-par-2026-03-13-tor",
      "question": "Will Torino FC win on 2026-03-13?",
      "category_label": "Science",
      "category_raw": null,
      "primary_outcome": "Yes",
      "probability": 43.5,
      "volume_24h": 791042.691355,
      "tags": [],
      "end_date": "2026-03-13T19:45:00Z",
      "created_at": "2026-02-28T00:00:27.36717Z",
      "days_to_deadline": 0.29601643256944443
    },
    {
      "market_id": "nhl-edm-stl-2026-03-13",
      "question": "Oilers vs. Blues",
      "category_label": "Science",
      "category_raw": null,
      "primary_outcome": "Yes",
      "probability": 56.49999999999999,
      "volume_24h": 786374.6898870013,
      "tags": [],
      "end_date": "2026-03-14T00:00:00Z",
      "created_at": "2026-02-14T16:30:09.162172Z",
      "days_to_deadline": 0.4730997658217593
    }
  ],
  "top_headlines": [
    "4 dead after U.S. Air Force refueler crashes in Iraq while supporting Iran war - The Washington Post",
    "What We Know About Michigan Synagogue Attack on Temple Israel - The New York Times",
    "ROTC students at Old Dominion University subdued and killed shooter who left 1 dead, 2 hurt - WTOP",
    "Scoop: Trump claimed in G7 call that Iran is \"about to surrender\" - Axios",
    "US Treasury Gives Green Light for Sale of More Russian Oil - Bloomberg.com",
    "California has no clear defense against Iran's 'naturally stealthy' drones - SFGATE",
    "Florida Legislature approves bill requiring voters to provide proof of citizenship - Florida Phoenix",
    "Vance was ‘skeptical’ voice in White House on Iran strikes - Politico"
  ],
  "trending_topics": [
    "Yahoo 100",
    "Top trending searches of 2025 revealed by Google. See what made the list.",
    "Gemini was Google’s top trending search term in 2025",
    "Google reveals the top trending searches of 2025"
  ]
}